umka-0.1.1.dist-info/METADATA
umka-0.1.1.dist-info/WHEEL
umka/fuzz/fuzz.py
umka/fuzz/__init__.py
umka/__init__.py
umka/test/fuzz/test_fuzz.py
umka/test/fuzz/__init__.py
umka/test/__init__.py
umka/fuzz/umka_rs.pypy39-pp73-x86_64-linux-gnu.so
umka-0.1.1.dist-info/RECORD
